_pyllamacpp.cpython-312-i386-linux-gnu.so
pyllamacpp/constants.py
pyllamacpp/_logger.py
pyllamacpp/cli.py
pyllamacpp/utils.py
pyllamacpp/webui.py
pyllamacpp/model.py
pyllamacpp/langchain_llm.py
pyllamacpp/__init__.py
pyllamacpp-2.4.3.dist-info/METADATA
pyllamacpp-2.4.3.dist-info/top_level.txt
pyllamacpp-2.4.3.dist-info/WHEEL
pyllamacpp-2.4.3.dist-info/RECORD
pyllamacpp-2.4.3.dist-info/LICENSE
pyllamacpp-2.4.3.dist-info/entry_points.txt
