Metadata-Version: 2.1
Name: pyllamacpp
Version: 2.4.3
Summary: Python bindings for llama.cpp
Author: Abdeladim Sadiki
License: MIT
Project-URL: Documentation, https://abdeladim-s.github.io/pyllamacpp
Project-URL: Source, https://github.com/abdeladim-s/pyllamacpp
Project-URL: Tracker, https://github.com/abdeladim-s/pyllamacpp/issues
Requires-Python: >=3.8
License-File: LICENSE
